bestpix/__init__.py
bestpix/application.py
bestpix/photos_interface.py
bestpix/templates/__init__.py
bestpix/templates/home.html
bestpix-1.5.8.data/scripts/cleanup
bestpix-1.5.8.data/scripts/reveal
bestpix-1.5.8.dist-info/LICENSE
bestpix-1.5.8.dist-info/METADATA
bestpix-1.5.8.dist-info/WHEEL
bestpix-1.5.8.dist-info/top_level.txt
bestpix-1.5.8.dist-info/RECORD
