Metadata-Version: 2.1
Name: bestpix
Version: 1.5.8
Summary: UNKNOWN
Home-page: https://github.com/mkchuprin/BestPix
Author: Michael Chuprin
Author-email: mkchuprin@gmail.com
License: GNU GPLv3
Platform: UNKNOWN
Requires-Python: >=3
